similarity_learning/__init__.py
similarity_learning/_modidx.py
similarity_learning/all.py
similarity_learning/facenet.py
similarity_learning/feature_space_plotting.py
similarity_learning/pair_matching.py
similarity_learning/siamese.py
similarity_learning/utils.py
similarity_learning-0.0.4.dist-info/LICENSE
similarity_learning-0.0.4.dist-info/METADATA
similarity_learning-0.0.4.dist-info/WHEEL
similarity_learning-0.0.4.dist-info/entry_points.txt
similarity_learning-0.0.4.dist-info/top_level.txt
similarity_learning-0.0.4.dist-info/RECORD
