Metadata-Version: 2.1
Name: similarity-learning
Version: 0.0.4
Summary: A fastai based framework for similarity learning
Home-page: https://github.com/Irad-Zehavi/similarity-learning
Author: iradz
Author-email: irad.zehavi@outlook.com
License: Apache Software License 2.0
Keywords: nbdev jupyter notebook python
Platform: UNKNOWN
Classifier: Development Status :: 4 - Beta
Classifier: Intended Audience :: Developers
Classifier: Natural Language :: English
Classifier: Programming Language :: Python :: 3.7
Classifier: Programming Language :: Python :: 3.8
Classifier: Programming Language :: Python :: 3.9
Classifier: Programming Language :: Python :: 3.10
Classifier: License :: OSI Approved :: Apache Software License
Requires-Python: >=3.7
Requires-Dist: facenet-pytorch
Requires-Dist: fastai
Requires-Dist: fastai-datasets
Requires-Dist: matplotlib
Provides-Extra: dev
Requires-Dist: nbdev ; extra == 'dev'
